hyo2.bagexplorer-1.3.2-py3.11-nspkg.pth
hyo2/bagexplorer/__init__.py
hyo2/bagexplorer/__main__.py
hyo2/bagexplorer/explorer.py
hyo2/bagexplorer/frame.py
hyo2/bagexplorer/text_ctrl.py
hyo2/bagexplorer/gui/__init__.py
hyo2/bagexplorer/gui/mainwin.py
hyo2_bagexplorer-1.3.2.dist-info/AUTHORS.rst
hyo2_bagexplorer-1.3.2.dist-info/LICENSE
hyo2_bagexplorer-1.3.2.dist-info/METADATA
hyo2_bagexplorer-1.3.2.dist-info/WHEEL
hyo2_bagexplorer-1.3.2.dist-info/entry_points.txt
hyo2_bagexplorer-1.3.2.dist-info/namespace_packages.txt
hyo2_bagexplorer-1.3.2.dist-info/top_level.txt
hyo2_bagexplorer-1.3.2.dist-info/RECORD
