Metadata-Version: 2.2
Name: hyo2.bagexplorer
Version: 1.3.2
Summary: An application to browse and manage BAG files.
Home-page: https://www.hydroffice.org/bag
Author: Giuseppe Masetti (CCOM,UNH)
Author-email: gmasetti@ccom.unh.edu
License: LGPLv3 license
Keywords: hydrography ocean mapping survey bag tools
Classifier: Development Status :: 5 - Production/Stable
Classifier: Intended Audience :: Science/Research
Classifier: Natural Language :: English
Classifier: License :: OSI Approved :: GNU Lesser General Public License v3 (LGPLv3)
Classifier: Operating System :: OS Independent
Classifier: Programming Language :: Python
Classifier: Programming Language :: Python :: 3
Classifier: Programming Language :: Python :: 3.9
Classifier: Programming Language :: Python :: 3.10
Classifier: Programming Language :: Python :: 3.11
Classifier: Programming Language :: Python :: 3.12
Classifier: Topic :: Scientific/Engineering :: GIS
Classifier: Topic :: Office/Business :: Office Suites
Requires-Python: >=3.9
License-File: LICENSE
License-File: AUTHORS.rst
Requires-Dist: hdf_compass>=0.7b16
Requires-Dist: hyo2.abc2>=2.4.0
Requires-Dist: hyo2.bag>=1.2.12
Dynamic: author
Dynamic: author-email
Dynamic: classifier
Dynamic: description
Dynamic: home-page
Dynamic: keywords
Dynamic: license
Dynamic: requires-dist
Dynamic: requires-python
Dynamic: summary
